spherical_projections/__init__.py
spherical_projections/default_projections.py
spherical_projections/exceptions.py
spherical_projections/logging_config.py
spherical_projections/processor.py
spherical_projections/registry.py
spherical_projections/utils.py
spherical_projections/base/__init__.py
spherical_projections/base/config.py
spherical_projections/base/grid.py
spherical_projections/base/interpolation.py
spherical_projections/base/registry.py
spherical_projections/base/strategy.py
spherical_projections/base/transform.py
spherical_projections/gnomonic/__init__.py
spherical_projections/gnomonic/config.py
spherical_projections/gnomonic/grid.py
spherical_projections/gnomonic/strategy.py
spherical_projections/gnomonic/transform.py
spherical_projections/mercator/__init__.py
spherical_projections/mercator/config.py
spherical_projections/mercator/grid.py
spherical_projections/mercator/strategy.py
spherical_projections/mercator/transform.py
spherical_projections-0.1.2b0.dist-info/METADATA
spherical_projections-0.1.2b0.dist-info/WHEEL
spherical_projections-0.1.2b0.dist-info/top_level.txt
spherical_projections-0.1.2b0.dist-info/RECORD
