Metadata-Version: 2.2
Name: spherical_projections
Version: 0.1.2b0
Summary: A spherical projection library for Python
Home-page: https://github.com/RobinsonGarcia/ProjectionRegistry/
Author: RLSGarcia
Author-email: RLSGarcia@icloud.com
Classifier: Programming Language :: Python :: 3
Classifier: Operating System :: OS Independent
Requires-Python: >=3.7
Requires-Dist: numpy>=1.20.0
Requires-Dist: pydantic>=1.10.0
Requires-Dist: scipy>=1.5.0
Requires-Dist: opencv-python>=4.5.0
Dynamic: author
Dynamic: author-email
Dynamic: classifier
Dynamic: description
Dynamic: description-content-type
Dynamic: home-page
Dynamic: requires-dist
Dynamic: requires-python
Dynamic: summary
